t2c/__init__.py
t2c/text2cron.py
t2c-0.0.6.dist-info/LICENSE
t2c-0.0.6.dist-info/METADATA
t2c-0.0.6.dist-info/WHEEL
t2c-0.0.6.dist-info/top_level.txt
t2c-0.0.6.dist-info/RECORD
