Metadata-Version: 2.1
Name: t2c
Version: 0.0.6
Summary: A Python Library that converts human readable text to Cron Expression.
Home-page: https://github.com/iguangyu/text2cron
Author: iguangyu
Author-email: oofheaven7@gmail.com
License: MIT
Keywords: text cron text langchain gpt npl
Classifier: Development Status :: 4 - Beta
Classifier: Intended Audience :: Developers
Classifier: Topic :: Scientific/Engineering
Classifier: License :: OSI Approved :: MIT License
Classifier: Programming Language :: Python :: 3
License-File: LICENSE
Requires-Dist: pendulum
Requires-Dist: cn2an
